chromaroute/__init__.py
chromaroute/config.py
chromaroute/embedding.py
chromaroute/py.typed
chromaroute/vector_store.py
chromaroute-0.2.3.dist-info/METADATA
chromaroute-0.2.3.dist-info/WHEEL
chromaroute-0.2.3.dist-info/licenses/LICENSE
chromaroute-0.2.3.dist-info/RECORD
