Metadata-Version: 2.4
Name: chromaroute
Version: 0.2.3
Summary: Provider-agnostic embedding functions for ChromaDB with OpenRouter and local fallback support.
Project-URL: Homepage, https://github.com/seanbrar/chromaroute
Project-URL: Repository, https://github.com/seanbrar/chromaroute
Project-URL: Changelog, https://github.com/seanbrar/chromaroute/blob/main/CHANGELOG.md
Project-URL: Issues, https://github.com/seanbrar/chromaroute/issues
Author-email: Sean Brar <hello@seanbrar.com>
License: MIT
License-File: LICENSE
Keywords: chromadb,embeddings,llm,openrouter,rag,vector-database
Classifier: Development Status :: 4 - Beta
Classifier: Intended Audience :: Developers
Classifier: Intended Audience :: Science/Research
Classifier: License :: OSI Approved :: MIT License
Classifier: Operating System :: OS Independent
Classifier: Programming Language :: Python :: 3
Classifier: Programming Language :: Python :: 3.11
Classifier: Programming Language :: Python :: 3.12
Classifier: Topic :: Scientific/Engineering :: Artificial Intelligence
Classifier: Typing :: Typed
Requires-Python: <3.14,>=3.11
Requires-Dist: chromadb>=1.4.1
Requires-Dist: python-dotenv>=1.2.1
Requires-Dist: requests>=2.32.5
Provides-Extra: dev
Requires-Dist: mypy>=1.19.1; extra == 'dev'
Requires-Dist: pytest-cov>=7.0.0; extra == 'dev'
Requires-Dist: pytest>=9.0.2; extra == 'dev'
Requires-Dist: ruff>=0.14.14; extra == 'dev'
Requires-Dist: types-requests>=2.32.4.20260107; extra == 'dev'
Provides-Extra: local
Requires-Dist: sentence-transformers>=5.2.0; extra == 'local'
